mutagenesis_visualization/.DS_Store
mutagenesis_visualization/__init__.py
mutagenesis_visualization/data/.DS_Store
mutagenesis_visualization/data/1a5r.pdb
mutagenesis_visualization/data/1erm.pdb
mutagenesis_visualization/data/1nd4.cif
mutagenesis_visualization/data/1nd4.pdb
mutagenesis_visualization/data/1xq8.pdb
mutagenesis_visualization/data/2grn.pdb
mutagenesis_visualization/data/5p21.pdb
mutagenesis_visualization/data/DMS_others.xlsx
mutagenesis_visualization/data/HRas166_GAPGEF.csv
mutagenesis_visualization/data/HRas166_GAPGEF_r0.csv
mutagenesis_visualization/data/HRas166_GAPGEF_r1.csv
mutagenesis_visualization/data/HRas166_GAP_r0.csv
mutagenesis_visualization/data/HRas166_GAP_r1.csv
mutagenesis_visualization/data/HRas166_RBD.csv
mutagenesis_visualization/data/HRas166_RBD_r0.csv
mutagenesis_visualization/data/HRas166_RBD_r1.csv
mutagenesis_visualization/data/HRas166_RBD_r2.csv
mutagenesis_visualization/data/HRas180_GAP_r0.csv
mutagenesis_visualization/data/HRas180_GAP_r1.csv
mutagenesis_visualization/data/HRas180_GAP_r2.csv
mutagenesis_visualization/data/HRas180_GAP_r3.csv
mutagenesis_visualization/data/HRas180_RBD_r0.csv
mutagenesis_visualization/data/HRas180_RBD_r1.csv
mutagenesis_visualization/data/HRas180_RBD_r2.csv
mutagenesis_visualization/data/HRas180_RBD_r3.csv
mutagenesis_visualization/data/HRas188_BaF3_r0.csv
mutagenesis_visualization/data/HRas188_BaF3_r1.csv
mutagenesis_visualization/data/KRas165_GAPGEF_r0.csv
mutagenesis_visualization/data/KRas165_GAPGEF_r1.csv
mutagenesis_visualization/data/KRas165_GAP_r0.csv
mutagenesis_visualization/data/KRas165_GAP_r1.csv
mutagenesis_visualization/data/KRas165_GAP_r2.csv
mutagenesis_visualization/data/KRas165_GEF_r0.csv
mutagenesis_visualization/data/KRas165_GEF_r1.csv
mutagenesis_visualization/data/KRas165_RBD_r0.csv
mutagenesis_visualization/data/KRas165_RBD_r1.csv
mutagenesis_visualization/data/KRas173Q61L_GAP_r0.csv
mutagenesis_visualization/data/KRas173Q61L_GAP_r1.csv
mutagenesis_visualization-1.0.0.dist-info/LICENSE
mutagenesis_visualization-1.0.0.dist-info/WHEEL
mutagenesis_visualization-1.0.0.dist-info/METADATA
mutagenesis_visualization-1.0.0.dist-info/RECORD
